LICENSE
MANIFEST.in
setup.cfg
setup.py
archipel_core.egg-info/PKG-INFO
archipel_core.egg-info/SOURCES.txt
archipel_core.egg-info/dependency_links.txt
archipel_core.egg-info/not-zip-safe
archipel_core.egg-info/requires.txt
archipel_core.egg-info/top_level.txt
archipelcore/__init__.py
archipelcore/__init__.pyc
archipelcore/archipelAvatarControllableEntity.py
archipelcore/archipelAvatarControllableEntity.pyc
archipelcore/archipelEntity.py
archipelcore/archipelEntity.pyc
archipelcore/archipelFileTransferCapableEntity.py
archipelcore/archipelHookableEntity.py
archipelcore/archipelHookableEntity.pyc
archipelcore/archipelPermissionCenter.py
archipelcore/archipelPermissionCenter.pyc
archipelcore/archipelPlugin.py
archipelcore/archipelPlugin.pyc
archipelcore/archipelRosterQueryableEntity.py
archipelcore/archipelRosterQueryableEntity.pyc
archipelcore/archipelTaggableEntity.py
archipelcore/archipelTaggableEntity.pyc
archipelcore/pubsub.py
archipelcore/pubsub.pyc
archipelcore/scriptutils.py
archipelcore/utils.py
archipelcore/utils.pyc